daoriontravelpkg/__init__.py
daoriontravelpkg/daorion.py
daoriontravelpkg-0.0.1.dist-info/LICENSE
daoriontravelpkg-0.0.1.dist-info/METADATA
daoriontravelpkg-0.0.1.dist-info/WHEEL
daoriontravelpkg-0.0.1.dist-info/top_level.txt
daoriontravelpkg-0.0.1.dist-info/RECORD
