Metadata-Version: 2.1
Name: daoriontravelpkg
Version: 0.0.1
Summary: For testing package
Home-page: https://github.com/SurjeetSingh2022/daorion_pdf_automation_version2
Author: Himangshu Biswas
Author-email: Himangshu.biswas@daorion.com
Classifier: Programming Language :: Python :: 3
Classifier: License :: OSI Approved :: MIT License
Classifier: Operating System :: OS Independent
Requires-Python: >=3.7
License-File: LICENSE
